Alt/Cameras/__init__.py
Alt/Cameras/CameraUsingAgent/CalibrationUtil.py
Alt/Cameras/CameraUsingAgent/CameraUsingAgentBase.py
Alt/Cameras/CameraUsingAgent/__init__.py
Alt/Cameras/Captures/Capture.py
Alt/Cameras/Captures/D435Capture.py
Alt/Cameras/Captures/FakeCapture.py
Alt/Cameras/Captures/OAKCapture.py
Alt/Cameras/Captures/OpenCVCapture.py
Alt/Cameras/Captures/__init__.py
Alt/Cameras/Captures/depthCamera.py
Alt/Cameras/Captures/utils.py
Alt/Cameras/Captures/tools/__init__.py
Alt/Cameras/Captures/tools/calibration.py
Alt/Cameras/Captures/tools/depthAiHelper.py
Alt/Cameras/Captures/tools/realsense2Helper.py
Alt/Cameras/Constants/__init__.py
Alt/Cameras/Constants/resolution.py
Alt/Cameras/Parameters/CameraCalibration.py
Alt/Cameras/Parameters/CameraConfig.py
Alt/Cameras/Parameters/CameraExtrinsics.py
Alt/Cameras/Parameters/CameraIntrinsics.py
Alt/Cameras/Parameters/__init__.py
Alt/Cameras/Proto/FramePacket.py
Alt/Cameras/Proto/__init__.py
Alt/Cameras/Proto/frameNetPacket.capnp
matrix_alt_cameras-0.0.1.dist-info/licenses/LICENSE.txt
matrix_alt_cameras-0.0.1.dist-info/METADATA
matrix_alt_cameras-0.0.1.dist-info/WHEEL
matrix_alt_cameras-0.0.1.dist-info/top_level.txt
matrix_alt_cameras-0.0.1.dist-info/RECORD
