Metadata-Version: 2.4
Name: Matrix-Alt-Cameras
Version: 0.0.1
Summary: Extension for the Matrix-Alt-Core package to add camera functionality
Home-page: https://github.com/Team488/Alt
Author: The Matrix 488
Author-email: 488matrix@gmail.com
Project-URL: Bug Tracker, https://github.com/Team488/Alt/issues
Project-URL: repository, https://github.com/Team488/Alt
Classifier: Programming Language :: Python :: 3
Classifier: License :: OSI Approved :: MIT License
Classifier: Operating System :: OS Independent
Requires-Python: >=3.9
License-File: LICENSE.txt
Requires-Dist: Matrix-Alt-Core==0.0.1
Requires-Dist: numpy==2.0.2
Requires-Dist: opencv-python==4.11.0.86
Requires-Dist: scipy==1.13.1
Requires-Dist: pycapnp==2.0.0
Requires-Dist: depthai==2.30.0.0
Requires-Dist: pyrealsense2==2.55.1.6486
Dynamic: license-file
